{"id":"AF9DF8DC-9F4A-4234-8C61-FDFEA37C60FF","validationEntity":{"analysedDataType":"auto","dataResult":{"createdDate":"2023-01-27T19:06:31Z"}},"modelEntity":{"createdDate":"2023-01-27T19:05:11Z","id":"062ABA6B-3DCB-4E3A-974D-4FD621B25588","experimentID":"AF9DF8DC-9F4A-4234-8C61-FDFEA37C60FF","title":"","modifiedDate":"2023-01-27T19:05:11Z","preferredFilename":"","version":"1.0","modelURL":"Models\/BetterRest%201.mlmodel"},"version":"1.0","settingEntity":{"augmentations":[],"suggestedColumns":["wake","estimatedSleep","coffee","actualSleep"],"targetColumn":"actualSleep","seedType":"default","transferLearningEmbeddingType":"dynamic","handPoseClassifierAugmentations":[],"featureNames":["wake","estimatedSleep","coffee"],"algorithmType":"maxEnt","harVideoAugmentations":0,"taskType":"generalRegresor","suggestedColumnValues":["31,500, 32,400, 26,100, 40,500, 19,800, 27,000, 20,700, 21,600, 41,400, 34,200, 21,600, 78,300, 32,400, 28,800, 18,900, 18,000, 28,800, 18,000, 7,200, 35,100, 24,300, 35,100, 34,200, 27,900, 30,600, 69,300, 35,100, 34,200, 34,200, 23,400","9.00, 5.00, 6.50, 8.75, 6.00, 7.50, 9.25, 6.00, 9.25, 6.75, 5.25, 9.25, 10.00, 8.75, 8.25, 6.25, 10.00, 6.25, 10.00, 9.50, 5.00, 7.50, 6.25, 8.00, 8.00, 6.50, 8.00, 10.00, 8.25, 8.00","6, 2, 10, 4, 3, 1, 1, 3, 5, 8, 3, 8, 2, 3, 1, 2, 3, 2, 1, 4, 2, 1, 1, 4, 3, 7, 4, 4, 1, 3","38,230, 20,180, 31,989, 35,258, 24,487, 28,300, 34,548, 24,557, 37,836, 31,340, 21,874, 40,405, 38,076, 34,265, 30,936, 24,665, 39,007, 24,578, 37,267, 37,878, 20,220, 28,400, 23,882, 32,427, 31,699, 29,670, 32,789, 39,792, 30,935, 31,701"],"handActionClassifierAugmentations":[],"suggestedColumnTypes":["Int","Double","Int","Int"],"styleTransferAlgorithmType":"image","generalRegressorType":{"auto":{}}},"state":"trained","trainingEntity":{"finishTime":"2023-01-27T19:08:46Z","validationResults":{"generalRegressor":{"maximumError":695.65104927134962,"rootMeanSquaredError":177.03138844482999}},"dataURL":"file:\/\/\/Users\/jensnikolaus\/Documents\/Dev\/Swift\/HackingWithSwift\/SwiftUI\/project4-files\/BetterRest.csv","dataResult":{"itemsCount":10000,"createdDate":"2023-01-27T19:06:31Z","dataURL":"file:\/\/\/Users\/jensnikolaus\/Documents\/Dev\/Swift\/HackingWithSwift\/SwiftUI\/project4-files\/BetterRest.csv","columnTypes":["Int","Double","Int","Int"],"columns":["wake","estimatedSleep","coffee","actualSleep"],"dataSourceID":"C16EB9BD-8083-4DD4-9761-4AD5531E11EA","columnValues":["31,500, 32,400, 26,100, 40,500, 19,800, 27,000, 20,700, 21,600, 41,400, 34,200, 21,600, 78,300, 32,400, 28,800, 18,900, 18,000, 28,800, 18,000, 7,200, 35,100, 24,300, 35,100, 34,200, 27,900, 30,600, 69,300, 35,100, 34,200, 34,200, 23,400","9.00, 5.00, 6.50, 8.75, 6.00, 7.50, 9.25, 6.00, 9.25, 6.75, 5.25, 9.25, 10.00, 8.75, 8.25, 6.25, 10.00, 6.25, 10.00, 9.50, 5.00, 7.50, 6.25, 8.00, 8.00, 6.50, 8.00, 10.00, 8.25, 8.00","6, 2, 10, 4, 3, 1, 1, 3, 5, 8, 3, 8, 2, 3, 1, 2, 3, 2, 1, 4, 2, 1, 1, 4, 3, 7, 4, 4, 1, 3","38,230, 20,180, 31,989, 35,258, 24,487, 28,300, 34,548, 24,557, 37,836, 31,340, 21,874, 40,405, 38,076, 34,265, 30,936, 24,665, 39,007, 24,578, 37,267, 37,878, 20,220, 28,400, 23,882, 32,427, 31,699, 29,670, 32,789, 39,792, 30,935, 31,701"],"targetRange":[19216,45224],"dataAnalysis":{"issues":[{"description":"Data has 10000 rows","severity":"info"}],"regressorAnalysis":{"targetRange":[19216,45224]},"classifierAnalysis":{},"summary":{"sampleCount":10000,"canUseValidation":1}}},"trainingResults":{"generalRegressor":{"maximumError":700.74479051892558,"rootMeanSquaredError":177.04579410036965}},"progress":[],"trainingAccuracy":177.04579410036965,"checkpointMetrics":{},"analysedDataType":"datasource","dataSourceID":"C16EB9BD-8083-4DD4-9761-4AD5531E11EA","snapshottableCheckpoints":{},"featureExtractionCheckpointMayBeAvailable":false,"validationAccuracy":177.03138844482999,"startTime":"2023-01-27T19:08:44Z"},"createdDate":"2023-01-27T19:05:11Z","evaluationContainerEntity":{"testingEvaluationEntity":{"id":"67fa50c1-cdca-4f0b-8782-b8e356a25de9","createdDate":"2023-01-27T19:05:11Z","dataResult":{"createdDate":"2023-01-27T19:06:31Z"},"analysedDataType":"none"},"createdDate":"2023-01-27T19:08:57Z","id":"1a71c0af-c598-4a60-b9df-82eb535fff75","trainingEvaluationEntity":{"evaluationResult":{"generalRegressor":{"maximumError":700.74479051892558,"rootMeanSquaredError":177.04579410036965}},"createdDate":"2023-01-27T19:05:11Z","id":"7ce2d4a7-cf4d-4933-9c85-786c0851eb2a","dataURL":"file:\/\/\/Users\/jensnikolaus\/Documents\/Dev\/Swift\/HackingWithSwift\/SwiftUI\/project4-files\/BetterRest.csv","dataSourceID":"C16EB9BD-8083-4DD4-9761-4AD5531E11EA","dataResult":{"itemsCount":10000,"createdDate":"2023-01-27T19:06:31Z","targetRange":[19216,45224],"dataURL":"file:\/\/\/Users\/jensnikolaus\/Documents\/Dev\/Swift\/HackingWithSwift\/SwiftUI\/project4-files\/BetterRest.csv","dataSourceID":"C16EB9BD-8083-4DD4-9761-4AD5531E11EA","dataAnalysis":{"issues":[{"description":"Data has 10000 rows","severity":"info"}],"regressorAnalysis":{"targetRange":[19216,45224]},"classifierAnalysis":{},"summary":{"sampleCount":10000,"canUseValidation":1}}},"analysedDataType":"none"},"previewType":"tabularRegressor","modifiedDate":"2023-01-27T19:08:57Z","validationEvaluationEntity":{"id":"1c01bfcf-0380-45a9-8b02-e1506762c05f","createdDate":"2023-01-27T19:05:11Z","dataResult":{"createdDate":"2023-01-27T19:06:31Z"},"analysedDataType":"auto","evaluationResult":{"generalRegressor":{"maximumError":695.65104927134962,"rootMeanSquaredError":177.03138844482999}}},"evaluationEntities":[{"id":"0b11fb68-dc5f-4706-ac8b-6122d3ec3a38","createdDate":"2023-01-27T19:08:57Z","dataResult":{},"analysedDataType":"none"}]},"activityEntities":["trainingDataAdded",[{"id":"E6BAF397-9FB5-4A1E-AF2E-765D0EA463CA","title":"Training Data Added","createdDate":"2023-01-27T19:06:31Z","event":"trainingDataAdded","subtitle":"BetterRest.csv"}],"experimentCreated",[{"id":"A909A7EA-6BF8-4387-870C-65B8FD7E3D44","title":"Model Source Created","createdDate":"2023-01-27T19:05:11Z","event":"experimentCreated","subtitle":"BetterRest 1"}],"trainingFinished",[{"id":"8F3F0E60-F4F9-4741-B600-15E829387B17","title":"Training Completed","createdDate":"2023-01-27T19:08:46Z","event":"trainingFinished","subtitle":"BetterRest 1"}],"trainingStarted",[{"id":"9A37B3B4-99F9-4B35-AD4B-A9B965E85031","title":"Training Started","createdDate":"2023-01-27T19:08:44Z","event":"trainingStarted","subtitle":"BetterRest 1"}]],"evaluationState":"uninitialized","title":"BetterRest 1","evaluationEntity":{"id":"fb38eacb-d85c-4905-8fa2-aff6e3686b00","analysedDataType":"none","dataResult":{}},"snapshotRole":{"withoutSnapshots":0},"contentDataResult":{"createdDate":"2023-01-27T19:06:31Z"},"modifiedDate":"2023-01-27T19:08:57Z","preferredFilename":"BetterRest 1"}